{"publishers": {"type": "<http://xmlns.com/foaf/0.1/Agent>", "id": "<http://bibliographica.org/entity/E117619>", "prefLabel": "Taschen", "name": "Taschen"}, "ISBD:hasNoteOnLanguage": ["Text in English, French and German."], "isbn": ["urn:isbn:9783822838693", "urn:isbn:3822838691"], "language": [{"rdf:value": ["ger"]}, {"rdf:value": ["eng"]}, {"rdf:value": ["fre"]}], "seeAlso": ["<http://www4.wiwiss.fu-berlin.de/bookmashup/books/3822838691>", "<http://www4.wiwiss.fu-berlin.de/bookmashup/books/9783822838693>", "<http://purl.org/NET/book/isbn/9783822838693#book>", "<http://purl.org/NET/book/isbn/3822838691#book>"], "issued": "c2005", "seealso": ["<http://www4.wiwiss.fu-berlin.de/bookmashup/books/3822838691>", "<http://www4.wiwiss.fu-berlin.de/bookmashup/books/9783822838693>", "<http://purl.org/NET/book/isbn/9783822838693#book>", "<http://purl.org/NET/book/isbn/3822838691#book>"], "title": "M.C. Escher", "bnb_id": "GBA516904", "placeofpublication": [{"label": "Ko\u0308ln"}, {"label": "London"}], "subjects": [{"type": "<http://www.w3.org/2004/02/skos/core#Concept>", "inscheme": "<http://id.loc.gov/authorities#conceptScheme>", "preflabel": "Prints, Dutch--20th century--Pictorial works."}, {"type": "<http://www.w3.org/2004/02/skos/core#Concept>", "inscheme": "<http://id.loc.gov/authorities#conceptScheme>", "preflabel": "Escher, M. C. (Maurits Cornelis), 1898-1972."}, {"type": "<http://www.w3.org/2004/02/skos/core#Concept>", "inscheme": "<http://id.loc.gov/authorities#conceptScheme>", "preflabel": "Escher, M. C. (Maurits Cornelis), 1898-1972--Criticism and interpretation."}, {"type": "<http://www.w3.org/2004/02/skos/core#Concept>", "inscheme": "<http://dewey.info/scheme/e22>", "notation": "769.92"}], "descriptions": "Formerly CIP.", "extent": {"label": "191 p"}, "series": [{"id": "<http://ckan.net/package/jiscopenbib-bl_bnb-1>"}, {"dc:title": ["Icons"], "type": "<http://purl.org/ontology/bibo/Series>", "id": "<http://bibliographica.org/series/S28282>"}], "creators": {"type": "<http://xmlns.com/foaf/0.1/Agent>", "id": "<http://bibliographica.org/entity/E117618>", "prefLabel": "Wiedemann, Julius.", "name": "Wiedemann, Julius."}, "type": ["<http://purl.org/ontology/bibo/Document>", "<http://purl.org/ontology/bibo/Book>"], "id": "<http://bibliographica.org/entry/BB3453409>", "foaf:isPrimaryTopicOf": ["<http://bibliographica.org/entry/BB3453409.ttl>", "<http://bibliographica.org/entry/BB3453409.nt>", "<http://bibliographica.org/entry/BB3453409.html>", "<http://bibliographica.org/entry/BB3453409.n3>", "<http://bibliographica.org/entry/BB3453409.rdf>"], "bl_id": "013119499"}